creator/__init__.py
creator/__version__.py
creator/agents/__init__.py
creator/agents/base.py
creator/agents/creator_agent.py
creator/agents/extractor_agent.py
creator/agents/interpreter_agent.py
creator/agents/refactor_agent.py
creator/agents/tester_agent.py
creator/app/server.py
creator/app/streamlit_app.py
creator/callbacks/__init__.py
creator/callbacks/base.py
creator/callbacks/buffer_manager.py
creator/callbacks/file_io.py
creator/callbacks/file_manager.py
creator/callbacks/rich_manager.py
creator/callbacks/streaming_stdout.py
creator/client/__init__.py
creator/client/command.py
creator/client/repl/__init__.py
creator/client/repl/app.py
creator/client/repl/completer.py
creator/client/repl/constants.py
creator/client/repl/handler.py
creator/client/repl/lexer.py
creator/client/repl/style.py
creator/code_interpreter/R.py
creator/code_interpreter/__init__.py
creator/code_interpreter/applescript.py
creator/code_interpreter/base.py
creator/code_interpreter/html.py
creator/code_interpreter/javascript.py
creator/code_interpreter/julia.py
creator/code_interpreter/python.py
creator/code_interpreter/safe_python.py
creator/code_interpreter/shell.py
creator/config/library.py
creator/config/load_config.py
creator/config/open_config.py
creator/config.yaml
creator/core/__init__.py
creator/core/core.py
creator/core/skill.py
creator/hub/__init__.py
creator/hub/huggingface.py
creator/llm/__init__.py
creator/llm/chatopenai_with_trim.py
creator/llm/llm_creator.py
creator/llm/tokentrim.py
creator/prompts/api_doc.md
creator/prompts/codeskill_function_schema.json
creator/prompts/creator_agent_prompt.md
creator/prompts/extractor_agent_prompt.md
creator/prompts/interpreter_agent_prompt.md
creator/prompts/refactor_agent_prompt.md
creator/prompts/tester_agent_prompt.md
creator/prompts/testsummary_function_schema.json
creator/prompts/tips_for_debugging_prompt.md
creator/prompts/tips_for_testing_prompt.md
creator/prompts/tips_for_veryfy_prompt.md
creator/retrivever/__init__.py
open_creator-0.1.2.dist-info/LICENSE
open_creator-0.1.2.dist-info/METADATA
open_creator-0.1.2.dist-info/WHEEL
open_creator-0.1.2.dist-info/entry_points.txt
open_creator-0.1.2.dist-info/RECORD
