Metadata-Version: 2.1
Name: open-creator
Version: 0.1.2
Summary: Build your costomized skill library
Author: JunminGONG
Author-email: junmingong@qq.com
Requires-Python: >=3.10,<4.0
Classifier: Programming Language :: Python :: 3
Classifier: Programming Language :: Python :: 3.10
Classifier: Programming Language :: Python :: 3.11
Requires-Dist: appdirs (>=1.4.4,<2.0.0)
Requires-Dist: fastapi (>=0.103.1,<0.104.0)
Requires-Dist: huggingface_hub (>=0.17.2,<0.18.0)
Requires-Dist: inquirer (>=3.1.3,<4.0.0)
Requires-Dist: langchain (>=0.0.317)
Requires-Dist: loguru (>=0.7.2,<0.8.0)
Requires-Dist: openai (>=0.28.1,<0.29.0)
Requires-Dist: prompt_toolkit (>=3.0.39,<4.0.0)
Requires-Dist: pydantic (>=2.0.3,<3.0.0)
Requires-Dist: pyreadline3 (>=3.4.1,<4.0.0) ; sys_platform == "win32"
Requires-Dist: python-dotenv (>=1.0.0,<2.0.0)
Requires-Dist: pyyaml (>=6.0.1,<7.0.0)
Requires-Dist: rich (>=13.5.2,<14.0.0)
Requires-Dist: streamlit (>=1.27.2,<2.0.0)
Requires-Dist: tiktoken (>=0.5.1,<0.6.0)
Requires-Dist: urllib3 (>=2.0.6,<3.0.0)
Requires-Dist: uvicorn (>=0.23.2,<0.24.0)
